configly/__init__.py
configly/client.py
configly_python_configly-0.0.2.dist-info/LICENSE
configly_python_configly-0.0.2.dist-info/METADATA
configly_python_configly-0.0.2.dist-info/WHEEL
configly_python_configly-0.0.2.dist-info/top_level.txt
configly_python_configly-0.0.2.dist-info/RECORD
